drf_aggregates/__init__.py
drf_aggregates/aggregates.py
drf_aggregates/exceptions.py
drf_aggregates/renderers.py
drf_aggregates-0.0.13.dist-info/METADATA
drf_aggregates-0.0.13.dist-info/WHEEL
drf_aggregates-0.0.13.dist-info/top_level.txt
drf_aggregates-0.0.13.dist-info/RECORD
