Metadata-Version: 2.1
Name: drf-aggregates
Version: 0.0.13
Summary: A Python package that exposes the Django model queryset aggregate functions to the DRF API.
Home-page: https://github.com/uptick/django-rest-framework-aggregates
Author: Fiona Lawrence, Jonathan Loo
Author-email: support@uptickhq.com
License: BSD
Keywords: drf,django-rest-framework,aggregates
Platform: UNKNOWN
Classifier: Development Status :: 2 - Pre-Alpha
Classifier: Environment :: Web Environment
Classifier: Framework :: Django
Classifier: Framework :: Django :: 1.11
Classifier: Intended Audience :: Developers
Classifier: License :: OSI Approved :: BSD License
Classifier: Operating System :: OS Independent
Classifier: Programming Language :: Python
Classifier: Programming Language :: Python :: 3.6
Classifier: Topic :: Office/Business
